{
  "resolvedId": "C:/Users/user/Desktop/portfolio-mkh/node_modules/nuxt/dist/app/composables/url.js",
  "transforms": [
    {
      "name": "vite:load-fallback",
      "result": "import { getRequestURL } from \"h3\";\nimport { joinURL } from \"ufo\";\nimport { useRuntimeConfig } from \"../nuxt.js\";\nimport { useRequestEvent } from \"./ssr.js\";\nexport function useRequestURL() {\n  if (import.meta.server) {\n    const url = getRequestURL(useRequestEvent());\n    url.pathname = joinURL(useRuntimeConfig().app.baseURL, url.pathname);\n    return url;\n  }\n  return new URL(window.location.href);\n}\n",
      "start": 1704142076056,
      "end": 1704142076411,
      "sourcemaps": null
    },
    {
      "name": "nuxt:layer-aliasing",
      "start": 1704142076411,
      "end": 1704142076411,
      "order": "pre"
    },
    {
      "name": "nuxt:layer-aliasing",
      "start": 1704142076411,
      "end": 1704142076411,
      "order": "pre"
    },
    {
      "name": "nuxt:server-devonly:transform",
      "start": 1704142076411,
      "end": 1704142076411,
      "order": "pre"
    },
    {
      "name": "nuxt:server-devonly:transform",
      "start": 1704142076411,
      "end": 1704142076411,
      "order": "pre"
    },
    {
      "name": "nuxt:client-fallback-auto-id",
      "start": 1704142076411,
      "end": 1704142076411,
      "order": "pre"
    },
    {
      "name": "vite:css",
      "start": 1704142076411,
      "end": 1704142076411,
      "order": "normal"
    },
    {
      "name": "vite:esbuild",
      "start": 1704142076411,
      "end": 1704142076411,
      "order": "normal"
    },
    {
      "name": "vite:json",
      "start": 1704142076411,
      "end": 1704142076411,
      "order": "normal"
    },
    {
      "name": "vite:worker",
      "start": 1704142076411,
      "end": 1704142076411,
      "order": "normal"
    },
    {
      "name": "vite:vue",
      "start": 1704142076411,
      "end": 1704142076411,
      "order": "normal"
    },
    {
      "name": "vite:vue-jsx",
      "start": 1704142076411,
      "end": 1704142076411,
      "order": "normal"
    },
    {
      "name": "replace",
      "start": 1704142076411,
      "end": 1704142076411,
      "order": "normal"
    },
    {
      "name": "replace",
      "start": 1704142076411,
      "end": 1704142076411,
      "order": "normal"
    },
    {
      "name": "nuxt:remove-plugin-metadata",
      "start": 1704142076411,
      "end": 1704142076411,
      "order": "normal"
    },
    {
      "name": "nuxt:remove-plugin-metadata",
      "start": 1704142076411,
      "end": 1704142076411,
      "order": "normal"
    },
    {
      "name": "nuxt:components:imports",
      "start": 1704142076411,
      "end": 1704142076411,
      "order": "normal"
    },
    {
      "name": "replace",
      "result": "import { getRequestURL } from \"h3\";\nimport { joinURL } from \"ufo\";\nimport { useRuntimeConfig } from \"../nuxt.js\";\nimport { useRequestEvent } from \"./ssr.js\";\nexport function useRequestURL() {\n  if (true) {\n    const url = getRequestURL(useRequestEvent());\n    url.pathname = joinURL(useRuntimeConfig().app.baseURL, url.pathname);\n    return url;\n  }\n  return new URL(window.location.href);\n}\n",
      "start": 1704142076411,
      "end": 1704142076411,
      "order": "normal",
      "sourcemaps": {
        "version": 3,
        "sources": [
          ""
        ],
        "names": [],
        "mappings": "AAAA,CAAC,CAAC,CAAC,CAAC,CAAC,CAAC,CAAC,CAAC,CAAC,CAAC,CAAC,CAAC,CAAC,CAAC,CAAC,CAAC,CAAC,CAAC,CAAC,CAAC,CAAC,CAAC,CAAC,CAAC,CAAC,CAAC,CAAC,CAAC,CAAC,CAAC,CAAC,CAAC,CAAC,CAAC,CAAC;AACnC,CAAC,CAAC,CAAC,CAAC,CAAC,CAAC,CAAC,CAAC,CAAC,CAAC,CAAC,CAAC,CAAC,CAAC,CAAC,CAAC,CAAC,CAAC,CAAC,CAAC,CAAC,CAAC,CAAC,CAAC,CAAC,CAAC,CAAC,CAAC,CAAC,CAAC;AAC9B,CAAC,CAAC,CAAC,CAAC,CAAC,CAAC,CAAC,CAAC,CAAC,CAAC,CAAC,CAAC,CAAC,CAAC,CAAC,CAAC,CAAC,CAAC,CAAC,CAAC,CAAC,CAAC,CAAC,CAAC,CAAC,CAAC,CAAC,CAAC,CAAC,CAAC,CAAC,CAAC,CAAC,CAAC,CAAC,CAAC,CAAC,CAAC,CAAC,CAAC,CAAC,CAAC,CAAC,CAAC,CAAC,CAAC;AAC9C,CAAC,CAAC,CAAC,CAAC,CAAC,CAAC,CAAC,CAAC,CAAC,CAAC,CAAC,CAAC,CAAC,CAAC,CAAC,CAAC,CAAC,CAAC,CAAC,CAAC,CAAC,CAAC,CAAC,CAAC,CAAC,CAAC,CAAC,CAAC,CAAC,CAAC,CAAC,CAAC,CAAC,CAAC,CAAC,CAAC,CAAC,CAAC,CAAC,CAAC,CAAC,CAAC,CAAC;AAC3C,CAAC,CAAC,CAAC,CAAC,CAAC,CAAC,CAAC,CAAC,CAAC,CAAC,CAAC,CAAC,CAAC,CAAC,CAAC,CAAC,CAAC,CAAC,CAAC,CAAC,CAAC,CAAC,CAAC,CAAC,CAAC,CAAC,CAAC,CAAC,CAAC,CAAC,CAAC,CAAC,CAAC;AACjC,CAAC,CAAC,CAAC,CAAC,CAAC,CAAC,IAAkB,CAAC,CAAC,CAAC;AAC3B,CAAC,CAAC,CAAC,CAAC,CAAC,CAAC,CAAC,CAAC,CAAC,CAAC,CAAC,CAAC,CAAC,CAAC,CAAC,CAAC,CAAC,CAAC,CAAC,CAAC,CAAC,CAAC,CAAC,CAAC,CAAC,CAAC,CAAC,CAAC,CAAC,CAAC,CAAC,CAAC,CAAC,CAAC,CAAC,CAAC,CAAC,CAAC,CAAC,CAAC,CAAC,CAAC,CAAC,CAAC,CAAC,CAAC,CAAC,CAAC,CAAC;AACjD,CAAC,CAAC,CAAC,CAAC,CAAC,CAAC,CAAC,CAAC,CAAC,CAAC,CAAC,CAAC,CAAC,CAAC,CAAC,CAAC,CAAC,CAAC,CAAC,CAAC,CAAC,CAAC,CAAC,CAAC,CAAC,CAAC,CAAC,CAAC,CAAC,CAAC,CAAC,CAAC,CAAC,CAAC,CAAC,CAAC,CAAC,CAAC,CAAC,CAAC,CAAC,CAAC,CAAC,CAAC,CAAC,CAAC,CAAC,CAAC,CAAC,CAAC,CAAC,CAAC,CAAC,CAAC,CAAC,CAAC,CAAC,CAAC,CAAC,CAAC,CAAC,CAAC,CAAC,CAAC,CAAC,CAAC,CAAC,CAAC,CAAC,CAAC,CAAC,CAAC,CAAC;AACzE,CAAC,CAAC,CAAC,CAAC,CAAC,CAAC,CAAC,CAAC,CAAC,CAAC,CAAC,CAAC,CAAC,CAAC,CAAC;AACf,CAAC,CAAC,CAAC;AACH,CAAC,CAAC,CAAC,CAAC,CAAC,CAAC,CAAC,CAAC,CAAC,CAAC,CAAC,CAAC,CAAC,CAAC,CAAC,CAAC,CAAC,CAAC,CAAC,CAAC,CAAC,CAAC,CAAC,CAAC,CAAC,CAAC,CAAC,CAAC,CAAC,CAAC,CAAC,CAAC,CAAC,CAAC,CAAC,CAAC,CAAC,CAAC,CAAC;AACvC,CAAC;"
      }
    },
    {
      "name": "ssr-styles",
      "start": 1704142076411,
      "end": 1704142076411,
      "order": "normal"
    },
    {
      "name": "vite:define",
      "result": "import { getRequestURL } from \"h3\";\nimport { joinURL } from \"ufo\";\nimport { useRuntimeConfig } from \"../nuxt.js\";\nimport { useRequestEvent } from \"./ssr.js\";\nexport function useRequestURL() {\n  if (true) {\n    const url = getRequestURL(useRequestEvent());\n    url.pathname = joinURL(useRuntimeConfig().app.baseURL, url.pathname);\n    return url;\n  }\n  return new URL((void 0).location.href);\n}\n",
      "start": 1704142076411,
      "end": 1704142076499,
      "order": "normal",
      "sourcemaps": "{\n  \"version\": 3,\n  \"sources\": [\"C:/Users/user/Desktop/portfolio-mkh/node_modules/nuxt/dist/app/composables/url.js\"],\n  \"sourcesContent\": [\"import { getRequestURL } from \\\"h3\\\";\\nimport { joinURL } from \\\"ufo\\\";\\nimport { useRuntimeConfig } from \\\"../nuxt.js\\\";\\nimport { useRequestEvent } from \\\"./ssr.js\\\";\\nexport function useRequestURL() {\\n  if (true) {\\n    const url = getRequestURL(useRequestEvent());\\n    url.pathname = joinURL(useRuntimeConfig().app.baseURL, url.pathname);\\n    return url;\\n  }\\n  return new URL(window.location.href);\\n}\\n\"],\n  \"mappings\": \"AAAA,SAAS,qBAAqB;AAC9B,SAAS,eAAe;AACxB,SAAS,wBAAwB;AACjC,SAAS,uBAAuB;AACzB,gBAAS,gBAAgB;AAC9B,MAAI,MAAM;AACR,UAAM,MAAM,cAAc,gBAAgB,CAAC;AAC3C,QAAI,WAAW,QAAQ,iBAAiB,EAAE,IAAI,SAAS,IAAI,QAAQ;AACnE,WAAO;AAAA,EACT;AACA,SAAO,IAAI,IAAI,SAAO,SAAS,IAAI;AACrC;\",\n  \"names\": []\n}\n"
    },
    {
      "name": "vite:css-post",
      "start": 1704142076499,
      "end": 1704142076499,
      "order": "normal"
    },
    {
      "name": "vite:build-html",
      "start": 1704142076499,
      "end": 1704142076499,
      "order": "normal"
    },
    {
      "name": "vite:worker-import-meta-url",
      "start": 1704142076500,
      "end": 1704142076500,
      "order": "normal"
    },
    {
      "name": "vite:asset-import-meta-url",
      "start": 1704142076500,
      "end": 1704142076500,
      "order": "normal"
    },
    {
      "name": "commonjs",
      "start": 1704142076500,
      "end": 1704142076500,
      "order": "normal"
    },
    {
      "name": "vite:dynamic-import-vars",
      "start": 1704142076500,
      "end": 1704142076500,
      "order": "normal"
    },
    {
      "name": "vite:import-glob",
      "start": 1704142076500,
      "end": 1704142076500,
      "order": "normal"
    },
    {
      "name": "nuxt:composable-keys",
      "start": 1704142076500,
      "end": 1704142076501,
      "order": "post"
    },
    {
      "name": "nuxt:composable-keys",
      "start": 1704142076500,
      "end": 1704142076501,
      "order": "post"
    },
    {
      "name": "nuxt:imports-transform",
      "start": 1704142076501,
      "end": 1704142076501,
      "order": "post"
    },
    {
      "name": "nuxt:imports-transform",
      "start": 1704142076501,
      "end": 1704142076502,
      "order": "post"
    },
    {
      "name": "unctx:transform",
      "start": 1704142076502,
      "end": 1704142076502,
      "order": "post"
    },
    {
      "name": "unctx:transform",
      "start": 1704142076502,
      "end": 1704142076502,
      "order": "post"
    },
    {
      "name": "nuxt:pages-macros-transform",
      "start": 1704142076503,
      "end": 1704142076503,
      "order": "post"
    },
    {
      "name": "nuxt:pages-macros-transform",
      "start": 1704142076503,
      "end": 1704142076503,
      "order": "post"
    },
    {
      "name": "nuxt:tree-shake-template",
      "start": 1704142076503,
      "end": 1704142076503,
      "order": "post"
    },
    {
      "name": "nuxt:components-loader",
      "start": 1704142076503,
      "end": 1704142076503,
      "order": "post"
    },
    {
      "name": "nuxt:tree-shake-composables:transform",
      "start": 1704142076503,
      "end": 1704142076503,
      "order": "post"
    },
    {
      "name": "vite:build-import-analysis",
      "start": 1704142076503,
      "end": 1704142076503,
      "order": "normal"
    },
    {
      "name": "vite:reporter",
      "start": 1704142076504,
      "end": 1704142076504,
      "order": "normal"
    }
  ]
}
